ansifier/__init__.py
ansifier/__main__.py
ansifier/ansify.py
ansifier/cli.py
ansifier/config.py
ansifier/input_formats.py
ansifier/output_formats.py
ansifier-0.1.2.dist-info/LICENSE
ansifier-0.1.2.dist-info/METADATA
ansifier-0.1.2.dist-info/WHEEL
ansifier-0.1.2.dist-info/entry_points.txt
ansifier-0.1.2.dist-info/top_level.txt
ansifier-0.1.2.dist-info/RECORD
