Metadata-Version: 2.1
Name: ansifier
Version: 0.1.2
Summary: A python package used to represent static & animated images as text
Author-email: Amelia Miner <ameliamminer@gmail.com>
Project-URL: Homepage, https://github.com/amminer/ansifier
Project-URL: Issues, https://github.com/amminer/ansifier/issues
Classifier: Programming Language :: Python :: 3
Classifier: License :: OSI Approved :: GNU General Public License v2 (GPLv2)
Classifier: Operating System :: OS Independent
Classifier: Development Status :: 4 - Beta
Classifier: Environment :: Console
Classifier: Natural Language :: English
Classifier: Topic :: Multimedia :: Graphics :: Graphics Conversion
Classifier: Topic :: Artistic Software
Classifier: Topic :: Utilities
Requires-Python: >=3.8
License-File: LICENSE
Requires-Dist: colorama ==0.4.6
Requires-Dist: Pillow >=9.0.1
Requires-Dist: filetype >=1.2.0
Requires-Dist: opencv-python >=4.10.0.0
